gnosisllm_knowledge/__init__.py
gnosisllm_knowledge/api/__init__.py
gnosisllm_knowledge/api/knowledge.py
gnosisllm_knowledge/api/memory.py
gnosisllm_knowledge/backends/__init__.py
gnosisllm_knowledge/backends/memory/__init__.py
gnosisllm_knowledge/backends/memory/indexer.py
gnosisllm_knowledge/backends/memory/searcher.py
gnosisllm_knowledge/backends/opensearch/__init__.py
gnosisllm_knowledge/backends/opensearch/agentic.py
gnosisllm_knowledge/backends/opensearch/config.py
gnosisllm_knowledge/backends/opensearch/indexer.py
gnosisllm_knowledge/backends/opensearch/mappings.py
gnosisllm_knowledge/backends/opensearch/memory/__init__.py
gnosisllm_knowledge/backends/opensearch/memory/client.py
gnosisllm_knowledge/backends/opensearch/memory/config.py
gnosisllm_knowledge/backends/opensearch/memory/setup.py
gnosisllm_knowledge/backends/opensearch/queries.py
gnosisllm_knowledge/backends/opensearch/searcher.py
gnosisllm_knowledge/backends/opensearch/setup.py
gnosisllm_knowledge/chunking/__init__.py
gnosisllm_knowledge/chunking/fixed.py
gnosisllm_knowledge/chunking/sentence.py
gnosisllm_knowledge/cli/__init__.py
gnosisllm_knowledge/cli/app.py
gnosisllm_knowledge/cli/commands/__init__.py
gnosisllm_knowledge/cli/commands/agentic.py
gnosisllm_knowledge/cli/commands/load.py
gnosisllm_knowledge/cli/commands/memory.py
gnosisllm_knowledge/cli/commands/search.py
gnosisllm_knowledge/cli/commands/setup.py
gnosisllm_knowledge/cli/display/__init__.py
gnosisllm_knowledge/cli/display/service.py
gnosisllm_knowledge/cli/utils/__init__.py
gnosisllm_knowledge/cli/utils/config.py
gnosisllm_knowledge/core/__init__.py
gnosisllm_knowledge/core/domain/__init__.py
gnosisllm_knowledge/core/domain/discovery.py
gnosisllm_knowledge/core/domain/document.py
gnosisllm_knowledge/core/domain/memory.py
gnosisllm_knowledge/core/domain/result.py
gnosisllm_knowledge/core/domain/search.py
gnosisllm_knowledge/core/domain/source.py
gnosisllm_knowledge/core/events/__init__.py
gnosisllm_knowledge/core/events/emitter.py
gnosisllm_knowledge-0.4.3.dist-info/METADATA
gnosisllm_knowledge-0.4.3.dist-info/WHEEL
gnosisllm_knowledge-0.4.3.dist-info/entry_points.txt
gnosisllm_knowledge-0.4.3.dist-info/RECORD
