Metadata-Version: 2.4
Name: gnosisllm-knowledge
Version: 0.4.3
Summary: Enterprise-grade knowledge loading, indexing, and search for Python
License: MIT
Keywords: knowledge-base,rag,semantic-search,vector-search,opensearch,llm,embeddings,enterprise
Author: David Marsa
Author-email: david.marsa@neomanex.com
Requires-Python: >=3.11,<4.0
Classifier: Development Status :: 4 - Beta
Classifier: Intended Audience :: Developers
Classifier: License :: OSI Approved :: MIT License
Classifier: Operating System :: OS Independent
Classifier: Programming Language :: Python :: 3
Classifier: Programming Language :: Python :: 3.11
Classifier: Programming Language :: Python :: 3.12
Classifier: Programming Language :: Python :: 3.13
Classifier: Topic :: Scientific/Engineering :: Artificial Intelligence
Classifier: Topic :: Text Processing :: Indexing
Classifier: Typing :: Typed
Classifier: Framework :: AsyncIO
Requires-Dist: aiohttp (>=3.13.2,<4.0.0)
Requires-Dist: httpx (>=0.28.1,<0.29.0)
Requires-Dist: opensearch-py (>=3.1.0,<4.0.0)
Requires-Dist: pydantic (>=2.12.5,<3.0.0)
Requires-Dist: pydantic-settings (>=2.12.0,<3.0.0)
Requires-Dist: python-dotenv (>=1.2.1,<2.0.0)
Requires-Dist: rich (>=13.7.0,<14.0.0)
Requires-Dist: typer (>=0.12.0,<1.0.0)
Project-URL: Changelog, https://github.com/gnosisllm/gnosisllm-knowledge/blob/main/CHANGELOG.md
Project-URL: Documentation, https://gnosisllm-knowledge.readthedocs.io
Project-URL: Homepage, https://github.com/gnosisllm/gnosisllm-knowledge
Project-URL: Repository, https://github.com/gnosisllm/gnosisllm-knowledge
